{
  "point": {
    "brands": {
      "Kim Khánh Việt Hùng": {
        "buy": 13280000.0,
        "sell": 13470000.0
      },
      "Ngọc Thịnh": {
        "buy": 13080000.0,
        "sell": 13230000.0
      }
    },
    "fetchedAt": "2026-07-16T08:11:24.474479+07:00",
    "time": "2026-07-16T08:00:00+07:00",
    "world": {
      "change": -14.82,
      "changePct": -0.36,
      "usd": 4048.07,
      "vndChi": 12913982.5
    }
  },
  "schemaVersion": 1,
  "updatedAt": "2026-07-16T08:11:24.474479+07:00"
}
