{
  "point": {
    "brands": {
      "Kim Khánh Việt Hùng": {
        "buy": 13280000.0,
        "sell": 13470000.0
      },
      "Ngọc Thịnh": {
        "buy": 13080000.0,
        "sell": 13230000.0
      }
    },
    "fetchedAt": "2026-07-16T00:40:27.278038+07:00",
    "time": "2026-07-16T00:00:00+07:00",
    "world": {
      "change": -5.8,
      "changePct": -0.14,
      "usd": 4057.09,
      "vndChi": 12942757.8
    }
  },
  "schemaVersion": 1,
  "updatedAt": "2026-07-16T00:40:27.278038+07:00"
}
